ai_native_core/__init__.py
ai_native_core/embedding.py
ai_native_core/model.py
ai_native_core/rerank.py
ai_native_core/extensions/__init__.py
ai_native_core/extensions/ext_redis.py
ai_native_core/extensions/ext_storage.py
ai_native_core/extensions/storage/__init__.py
ai_native_core/extensions/storage/aliyun_oss_storage.py
ai_native_core/extensions/storage/aws_s3_storage.py
ai_native_core/extensions/storage/base_storage.py
ai_native_core/extensions/storage/huawei_obs_storage.py
ai_native_core/extensions/storage/storage_type.py
ai_native_core/extensions/storage/tencent_cos_storage.py
ai_native_core/extensions/tests/__init__.py
ai_native_core/extensions/tests/integration_tests/__init__.py
ai_native_core/extensions/tests/integration_tests/test_ext_storage.py
ai_native_core/extensions/tests/unit_tests/__init__.py
ai_native_core/extractor/__init__.py
ai_native_core/extractor/pdf.py
ai_native_core/extractor/word.py
ai_native_core/extractor/tests/__init__.py
ai_native_core/extractor/tests/unit_tests/__init__.py
ai_native_core/extractor/tests/unit_tests/test_word.py
ai_native_core/indexing/__init__.py
ai_native_core/indexing/de_duplication.py
ai_native_core/indexing/index.py
ai_native_core/indexing/splitter.py
ai_native_core/indexing/weaviate_client.py
ai_native_core/indexing/iot_bot_tools/__init__.py
ai_native_core/indexing/iot_bot_tools/exit.py
ai_native_core/indexing/iot_bot_tools/volume.py
ai_native_core/indexing/tests/__init__.py
ai_native_core/indexing/tests/test_index.py
ai_native_core/indexing/tests/test_iot_bot_tools.py
ai_native_core/indexing/tests/test_splitter.py
ai_native_core/indexing/tests/test_tool_index.py
ai_native_core/indexing/tests/test_tool_splitter.py
ai_native_core/tests/__init__.py
ai_native_core/tests/test_embedding.py
ai_native_core/tests/test_langgraph_sdk.py
ai_native_core/tests/test_model.py
ai_native_core/tests/test_rerank.py
ai_native_core/utils/__init__.py
ai_native_core/utils/iot_bot.py
ai_native_core/utils/show_graph.py
ai_native_core-0.0.6.dist-info/METADATA
ai_native_core-0.0.6.dist-info/WHEEL
ai_native_core-0.0.6.dist-info/top_level.txt
ai_native_core-0.0.6.dist-info/RECORD
