Metadata-Version: 2.2
Name: ai-native-core
Version: 0.0.6
Summary: A LLMOps Platform's native core
Author: Tangyuan
Author-email: 17348241417@163.com
Classifier: Programming Language :: Python :: 3.12
Classifier: Operating System :: OS Independent
Requires-Python: >=3.12
Requires-Dist: langchain~=0.3.27
Requires-Dist: langchain-openai~=0.3.28
Requires-Dist: langchain-community~=0.3.27
Requires-Dist: langchain-weaviate~=0.0.5
Requires-Dist: langgraph~=0.4.10
Requires-Dist: langgraph-prebuilt~=0.2.3
Requires-Dist: langgraph-runtime-inmem~=0.4.0
Requires-Dist: allure-pytest
Requires-Dist: redis
Requires-Dist: tang-yuan-mlops-sdk
Requires-Dist: python-dotenv
Dynamic: author
Dynamic: author-email
Dynamic: classifier
Dynamic: description
Dynamic: description-content-type
Dynamic: requires-dist
Dynamic: requires-python
Dynamic: summary
